PutioMount/__init__.py
PutioMount-2.dist-info/LICENSE
PutioMount-2.dist-info/METADATA
PutioMount-2.dist-info/WHEEL
PutioMount-2.dist-info/top_level.txt
PutioMount-2.dist-info/RECORD
